{
  "success": true,
  "schema_version": "2026-03-15.multimodal-intake.checkpoint9",
  "execution": {
    "status": "success",
    "summary": {
      "attempted_operation_count": 3,
      "applied_operation_count": 3,
      "failed_operation_count": 0
    },
    "preflight_crosscheck": {
      "status": "mismatch_error",
      "mismatch_classes": [
        "preflight_can_run_regressed",
        "preflight_issue_count_regressed_after_success"
      ],
      "invariants": {
        "issue_count_delta": 2,
        "regressed_can_run": true
      }
    },
    "parity_report": {
      "status": "mismatch_error",
      "preflight_crosscheck_status": "mismatch_error",
      "geant4_compatibility_confidence": {
        "label": "low",
        "score": 25,
        "reason_codes": [
          "preflight_mismatch_error",
          "execution_status_success",
          "preflight_can_run_regressed",
          "preflight_issue_count_regressed_after_success"
        ]
      },
      "summary": {
        "high_signal_mismatch_count": 2,
        "high_signal_mismatch_classes": [
          "preflight_can_run_regressed",
          "preflight_issue_count_regressed_after_success"
        ],
        "affected_operation_group_count": 2,
        "issue_count_delta": 2,
        "regressed_can_run": true
      },
      "issue_code_delta": {
        "added_issue_codes": [
          "placement_hierarchy_cycle",
          "unknown_world_volume_reference"
        ],
        "increased_issue_codes": [],
        "resolved_issue_codes": [],
        "reduced_issue_codes": []
      },
      "issue_code_family_correlations": {
        "summary": {
          "changed_issue_code_count": 2,
          "with_observed_overlap_count": 0,
          "without_observed_overlap_count": 2,
          "confidence_counts": {
            "high": 0,
            "medium": 2,
            "low": 0
          }
        },
        "entries": [
          {
            "issue_code": "placement_hierarchy_cycle",
            "change_kind": "added",
            "delta": 1,
            "confidence": "medium",
            "reason_codes": [
              "exact_issue_code_family_match",
              "no_overlap_with_executed_operation_groups"
            ],
            "likely_operation_family_ids": [
              "other_mutations"
            ],
            "likely_operation_families": [
              {
                "group_id": "other_mutations",
                "label": "Other mutation operations",
                "observed_in_execution": false
              }
            ],
            "observed_overlap_operation_family_ids": []
          },
          {
            "issue_code": "unknown_world_volume_reference",
            "change_kind": "added",
            "delta": 1,
            "confidence": "medium",
            "reason_codes": [
              "exact_issue_code_family_match",
              "no_overlap_with_executed_operation_groups"
            ],
            "likely_operation_family_ids": [
              "other_mutations"
            ],
            "likely_operation_families": [
              {
                "group_id": "other_mutations",
                "label": "Other mutation operations",
                "observed_in_execution": false
              }
            ],
            "observed_overlap_operation_family_ids": []
          }
        ]
      },
      "operation_groups": [
        {
          "group_id": "dimension_hints",
          "label": "Dimension hint mutations",
          "operation_count": 2,
          "applied_operation_count": 2,
          "failed_operation_count": 0,
          "not_executed_operation_count": 0,
          "operation_indices": [0, 1],
          "operation_types": ["apply_region_dimension_hint"],
          "tool_names": ["manage_define"],
          "status_codes": ["applied"]
        },
        {
          "group_id": "material_updates",
          "label": "Material update mutations",
          "operation_count": 1,
          "applied_operation_count": 1,
          "failed_operation_count": 0,
          "not_executed_operation_count": 0,
          "operation_indices": [2],
          "operation_types": ["apply_region_material_hint"],
          "tool_names": ["manage_logical_volume"],
          "status_codes": ["applied"]
        }
      ],
      "high_signal_mismatches": [
        {
          "mismatch_class": "preflight_can_run_regressed",
          "severity": "error",
          "message": "Preflight can_run regressed after multimodal execution.",
          "affected_operation_groups": [
            {
              "group_id": "dimension_hints",
              "label": "Dimension hint mutations",
              "operation_count": 2,
              "applied_operation_count": 2,
              "failed_operation_count": 0,
              "status_codes": ["applied"]
            },
            {
              "group_id": "material_updates",
              "label": "Material update mutations",
              "operation_count": 1,
              "applied_operation_count": 1,
              "failed_operation_count": 0,
              "status_codes": ["applied"]
            }
          ]
        }
      ]
    }
  }
}
